{"last_node_id": 194, "last_link_id": 151, "nodes": [{"id": 82, "type": "mxSlider", "pos": [-430.98622558421545, 72.65155428173787], "size": [555.747770729814, 30], "flags": {}, "order": 0, "mode": 4, "outputs": [{"name": "", "type": "INT", "links": [89], "shape": 3, "slot_index": 0}], "title": "Resolution", "properties": {"value": 480, "min": 480, "max": 4320, "step": 1, "decimals": 0, "snap": true, "Node name for S&R": "mxSlider"}, "widgets_values": [480, 480, 0], "color": "#223", "bgcolor": "#335"}, {"id": 16, "type": "VAEDecode", "pos": [622, 13], "size": {"0": 140, "1": 46}, "flags": {"collapsed": true}, "order": 45, "mode": 4, "inputs": [{"name": "samples", "type": "LATENT", "link": 20}, {"name": "vae", "type": "VAE", "link": 21}], "outputs": [{"name": "IMAGE", "type": "IMAGE", "links": [60], "shape": 3, "slot_index": 0}], "properties": {"Node name for S&R": "VAEDecode"}, "color": "#ffb614", "bgcolor": "#ffa200"}, {"id": 115, "type": "ImpactFloat", "pos": [-1386, -987], "size": {"0": 315, "1": 58}, "flags": {}, "order": 1, "mode": 0, "outputs": [{"name": "FLOAT", "type": "FLOAT", "links": [114], "shape": 3, "slot_index": 0}], "title": "CFG", "properties": {"Node name for S&R": "ImpactFloat"}, "widgets_values": [7.5]}, {"id": 119, "type": "ImpactFloat", "pos": [-1382, -861], "size": {"0": 315, "1": 58}, "flags": {}, "order": 2, "mode": 0, "outputs": [{"name": "FLOAT", "type": "FLOAT", "links": [118], "shape": 3, "slot_index": 0}], "title": "FPS", "properties": {"Node name for S&R": "ImpactFloat"}, "widgets_values": [10]}, {"id": 122, "type": "LoadEmbedding", "pos": [985.3813987150459, -1014.9665136932562], "size": {"0": 315.1015930175781, "1": 102}, "flags": {}, "order": 3, "mode": 4, "inputs": [{"name": "text", "type": "STRING", "link": null, "widget": {"name": "text"}}], "outputs": [{"name": "text", "type": "STRING", "links": null, "shape": 3}, {"name": "Preview Image", "type": "IMAGE", "links": null, "shape": 3}], "properties": {"Node name for S&R": "LoadEmbedding"}, "widgets_values": ["", "TLA\\0.9Merge\\0.9Merge.pt", 1]}, {"id": 123, "type": "HypernetworkLoader", "pos": [984.3813987150459, -866.9665136932562], "size": {"0": 315, "1": 82}, "flags": {}, "order": 4, "mode": 4, "inputs": [{"name": "model", "type": "MODEL", "link": null}], "outputs": [{"name": "MODEL", "type": "MODEL", "links": null, "shape": 3}], "properties": {"Node name for S&R": "HypernetworkLoader"}, "widgets_values": ["TLA\\hypernetV0.1_pre-exposure1\\V0.1_pre-exposure.pt", 1]}, {"id": 120, "type": "Anything Everywhere?", "pos": [-1363, 154], "size": {"0": 315, "1": 148}, "flags": {"collapsed": true}, "order": 20, "mode": 0, "inputs": [{"name": "FLOAT", "type": "*", "link": 118, "color_on": ""}], "title": "Wifi FPS", "properties": {"group_restricted": 0, "color_restricted": 0, "Node name for S&R": "Anything Everywhere?"}, "widgets_values": ["", "frame_rate", "", "10.0"]}, {"id": 116, "type": "Anything Everywhere?", "pos": [-1362, 114], "size": {"0": 315, "1": 148}, "flags": {"collapsed": true}, "order": 19, "mode": 0, "inputs": [{"name": "FLOAT", "type": "*", "link": 114, "color_on": ""}], "title": "Wifi CFG", "properties": {"group_restricted": 0, "color_restricted": 0, "Node name for S&R": "Anything Everywhere?"}, "widgets_values": ["", "cfg", "", "7.5"]}, {"id": 65, "type": "VHS_VideoCombine", "pos": [162, 361], "size": [211.6373748779297, 420.1377335590731], "flags": {}, "order": 41, "mode": 4, "inputs": [{"name": "images", "type": "IMAGE", "link": 72}, {"name": "audio", "type": "VHS_AUDIO", "link": 73}, {"name": "meta_batch", "type": "VHS_BatchManager", "link": null}, {"name": "frame_rate", "type": "FLOAT", "link": null, "widget": {"name": "frame_rate"}}], "outputs": [{"name": "Filenames", "type": "VHS_FILENAMES", "links": null, "shape": 3}], "title": "Video Output 4 (BG)", "properties": {"Node name for S&R": "VHS_VideoCombine"}, "widgets_values": {"frame_rate": 8, "loop_count": 0, "filename_prefix": "AnimateDiff", "format": "image/gif", "pingpong": false, "save_output": true, "videopreview": {"hidden": false, "paused": false, "params": {"filename": "AnimateDiff_00010.gif", "subfolder": "", "type": "output", "format": "image/gif"}}}}, {"id": 63, "type": "BRIA_RMBG_ModelLoader_Zho", "pos": [159, 102], "size": {"0": 219.7683563232422, "1": 26}, "flags": {"collapsed": false}, "order": 5, "mode": 4, "outputs": [{"name": "rmbgmodel", "type": "RMBGMODEL", "links": [70], "shape": 3, "slot_index": 0}], "properties": {"Node name for S&R": "BRIA_RMBG_ModelLoader_Zho"}}, {"id": 61, "type": "ImpactImageBatchToImageList", "pos": [479, 217], "size": {"0": 210, "1": 26}, "flags": {"collapsed": false}, "order": 27, "mode": 4, "inputs": [{"name": "image", "type": "IMAGE", "link": 68}], "outputs": [{"name": "IMAGE", "type": "IMAGE", "links": [69], "shape": 6, "slot_index": 0}], "properties": {"Node name for S&R": "ImpactImageBatchToImageList"}}, {"id": 64, "type": "ImageListToImageBatch", "pos": [482, 131], "size": {"0": 210, "1": 26}, "flags": {"collapsed": false}, "order": 37, "mode": 4, "inputs": [{"name": "images", "type": "IMAGE", "link": 71}], "outputs": [{"name": "IMAGE", "type": "IMAGE", "links": [72], "shape": 3, "slot_index": 0}], "properties": {"Node name for S&R": "ImageListToImageBatch"}}, {"id": 62, "type": "BRIA_RMBG_Zho", "pos": [192, 196], "size": {"0": 205.96592712402344, "1": 46}, "flags": {"collapsed": false}, "order": 32, "mode": 4, "inputs": [{"name": "rmbgmodel", "type": "RMBGMODEL", "link": 70}, {"name": "image", "type": "IMAGE", "link": 69}], "outputs": [{"name": "image", "type": "IMAGE", "links": [71], "shape": 3, "slot_index": 0}, {"name": "mask", "type": "MASK", "links": null, "shape": 3}], "properties": {"Node name for S&R": "BRIA_RMBG_Zho"}}, {"id": 102, "type": "Anything Everywhere3", "pos": [-1411, 71], "size": {"0": 599.5977172851562, "1": 66}, "flags": {"collapsed": true}, "order": 35, "mode": 0, "inputs": [{"name": "MODEL", "type": "*", "link": 108, "color_on": "#dc322f"}, {"name": "CLIP", "type": "*", "link": 110, "color_on": "#2AB7CA"}, {"name": "VAE", "type": "*", "link": 111, "color_on": "#facfad"}], "title": "Main Wifi(Model/Clip/Lora/Vae)", "properties": {"group_restricted": 0, "color_restricted": 0, "Node name for S&R": "Anything Everywhere3"}, "widgets_values": []}, {"id": 11, "type": "VAELoader", "pos": [-1184, 402], "size": {"0": 395.8094177246094, "1": 58}, "flags": {"collapsed": false}, "order": 6, "mode": 0, "outputs": [{"name": "VAE", "type": "VAE", "links": [13, 21, 111], "shape": 3, "slot_index": 0}], "properties": {"Node name for S&R": "VAELoader"}, "widgets_values": ["vaeRealanimark_vaeRealanimark.safetensors"], "color": "#232", "bgcolor": "#353"}, {"id": 5, "type": "CheckpointLoaderSimple", "pos": [-1251, 501], "size": {"0": 468.2551574707031, "1": 98}, "flags": {"collapsed": false}, "order": 7, "mode": 0, "outputs": [{"name": "MODEL", "type": "MODEL", "links": [94, 106], "shape": 3, "slot_index": 0}, {"name": "CLIP", "type": "CLIP", "links": [96, 97, 104, 107], "shape": 3, "slot_index": 1}, {"name": "VAE", "type": "VAE", "links": null, "shape": 3}], "properties": {"Node name for S&R": "CheckpointLoaderSimple"}, "widgets_values": ["3rd_P\\animeScreencapStyle_assV14Beta.safetensors"], "color": "#232", "bgcolor": "#353"}, {"id": 8, "type": "KSampler", "pos": [-1163, -690], "size": {"0": 373.8988342285156, "1": 230}, "flags": {"collapsed": true}, "order": 36, "mode": 4, "inputs": [{"name": "model", "type": "MODEL", "link": 11}, {"name": "positive", "type": "CONDITIONING", "link": 101, "slot_index": 1}, {"name": "negative", "type": "CONDITIONING", "link": 99}, {"name": "latent_image", "type": "LATENT", "link": 77}, {"name": "seed", "type": "INT", "link": 84, "widget": {"name": "seed"}}, {"name": "steps", "type": "INT", "link": 86, "widget": {"name": "steps"}}, {"name": "cfg", "type": "FLOAT", "link": null, "widget": {"name": "cfg"}}], "outputs": [{"name": "LATENT", "type": "LATENT", "links": [12, 25], "shape": 3, "slot_index": 0}], "title": "(Pre-Output) KSampler", "properties": {"Node name for S&R": "KSampler"}, "widgets_values": [351863803273899, "randomize", 30, 7.5, "euler_ancestral", "karras", 1], "color": "#232", "bgcolor": "#353"}, {"id": 75, "type": "EmptyLatentImage", "pos": [-1393, -690], "size": {"0": 210, "1": 74}, "flags": {"collapsed": true}, "order": 26, "mode": 4, "inputs": [{"name": "width", "type": "INT", "link": 74, "widget": {"name": "width"}}, {"name": "height", "type": "INT", "link": 75, "widget": {"name": "height"}}, {"name": "batch_size", "type": "INT", "link": 76, "widget": {"name": "batch_size"}}], "outputs": [{"name": "LATENT", "type": "LATENT", "links": [77], "shape": 3, "slot_index": 0}], "properties": {"Node name for S&R": "EmptyLatentImage"}, "widgets_values": [512, 512, 1], "color": "#232", "bgcolor": "#353"}, {"id": 12, "type": "VAEDecode", "pos": [-1226, -626], "size": {"0": 146.11231994628906, "1": 46}, "flags": {"collapsed": true}, "order": 39, "mode": 4, "inputs": [{"name": "samples", "type": "LATENT", "link": 12}, {"name": "vae", "type": "VAE", "link": 13}], "outputs": [{"name": "IMAGE", "type": "IMAGE", "links": [61], "shape": 3, "slot_index": 0}], "properties": {"Node name for S&R": "VAEDecode"}, "color": "#232", "bgcolor": "#353"}, {"id": 54, "type": "ImageScaleBy", "pos": [1062, 510], "size": {"0": 259.5926513671875, "1": 82}, "flags": {}, "order": 34, "mode": 0, "inputs": [{"name": "image", "type": "IMAGE", "link": 65}], "outputs": [{"name": "IMAGE", "type": "IMAGE", "links": [66], "shape": 3, "slot_index": 0}], "properties": {"Node name for S&R": "ImageScaleBy"}, "widgets_values": ["nearest-exact", 1], "color": "#432", "bgcolor": "#653"}, {"id": 105, "type": "CLIPSetLastLayer", "pos": [-1416, 210], "size": {"0": 210, "1": 58}, "flags": {}, "order": 30, "mode": 0, "inputs": [{"name": "clip", "type": "CLIP", "link": 109}], "outputs": [{"name": "CLIP", "type": "CLIP", "links": [110], "shape": 3, "slot_index": 0}], "properties": {"Node name for S&R": "CLIPSetLastLayer"}, "widgets_values": [-2], "color": "#232", "bgcolor": "#353"}, {"id": 67, "type": "mxSlider", "pos": [-974, -730], "size": [1555.5673002025057, 30], "flags": {}, "order": 8, "mode": 4, "outputs": [{"name": "", "type": "INT", "links": [76], "shape": 3, "slot_index": 0}], "title": "Totality of Frames", "properties": {"value": 100, "min": 100, "max": 500, "step": 1, "decimals": 0, "snap": true, "Node name for S&R": "mxSlider"}, "widgets_values": [100, 100, 0], "color": "#232", "bgcolor": "#353"}, {"id": 80, "type": "mxSlider", "pos": [-976, -661], "size": [1557.5673002025057, 30], "flags": {}, "order": 9, "mode": 4, "outputs": [{"name": "", "type": "INT", "links": [85, 86], "shape": 3, "slot_index": 0}], "title": "Steps/Quality", "properties": {"value": 10, "min": 0, "max": 200, "step": 1, "decimals": 0, "snap": true, "Node name for S&R": "mxSlider"}, "widgets_values": [10, 10, 0], "color": "#232", "bgcolor": "#353"}, {"id": 13, "type": "PrimitiveNode", "pos": [-1386, -628], "size": {"0": 210, "1": 82}, "flags": {"collapsed": true}, "order": 10, "mode": 4, "outputs": [{"name": "INT", "type": "INT", "links": [83, 84], "slot_index": 0, "widget": {"name": "seed"}}], "title": "\ud83c\udf31Seed\ud83c\udf31", "properties": {"Run widget replace on values": false}, "widgets_values": [351863803273899, "fixed"], "color": "#232", "bgcolor": "#353"}, {"id": 103, "type": "Power Lora Loader (rgthree)", "pos": {"0": -1006, "1": -946, "2": 0, "3": 0, "4": 0, "5": 0, "6": 0, "7": 0, "8": 0, "9": 0}, "size": {"0": 351.2596740722656, "1": 142}, "flags": {}, "order": 24, "mode": 4, "inputs": [{"name": "model", "type": "MODEL", "link": 106, "dir": 3}, {"name": "clip", "type": "CLIP", "link": 107, "dir": 3}], "outputs": [{"name": "MODEL", "type": "MODEL", "links": [108], "shape": 3, "dir": 4, "slot_index": 0}, {"name": "CLIP", "type": "CLIP", "links": [109], "shape": 3, "dir": 4, "slot_index": 1}], "properties": {"Show Strengths": "Single Strength"}, "widgets_values": [null, {"type": "PowerLoraLoaderHeaderWidget"}, {"on": true, "lora": "NSFW\\nswf_last.safetensors", "strength": 1, "strengthTwo": null}, null, ""], "color": "#323", "bgcolor": "#535"}, {"id": 76, "type": "ADE_AnimateDiffLoRALoader", "pos": [-590, -921], "size": {"0": 536.0271606445312, "1": 82}, "flags": {}, "order": 11, "mode": 4, "inputs": [{"name": "prev_motion_lora", "type": "MOTION_LORA", "link": null}], "outputs": [{"name": "MOTION_LORA", "type": "MOTION_LORA", "links": [90], "shape": 3, "slot_index": 0}], "properties": {"Node name for S&R": "ADE_AnimateDiffLoRALoader"}, "widgets_values": ["Cam\\v2_lora_ZoomIn.ckpt", 1], "color": "#323", "bgcolor": "#535"}, {"id": 85, "type": "ADE_AnimateDiffLoRALoader", "pos": [11, -923], "size": {"0": 530.9606323242188, "1": 82}, "flags": {}, "order": 25, "mode": 4, "inputs": [{"name": "prev_motion_lora", "type": "MOTION_LORA", "link": 90}], "outputs": [{"name": "MOTION_LORA", "type": "MOTION_LORA", "links": [95], "shape": 3, "slot_index": 0}], "properties": {"Node name for S&R": "ADE_AnimateDiffLoRALoader"}, "widgets_values": ["Action_Made_By_Person\\walkingMotionLoras_casualWalkingV1.safetensors", 1], "color": "#323", "bgcolor": "#535"}, {"id": 91, "type": "Prompts", "pos": [-1394, -579], "size": {"0": 962.5682373046875, "1": 584.7935791015625}, "flags": {}, "order": 21, "mode": 4, "inputs": [{"name": "clip", "type": "CLIP", "link": 96}], "outputs": [{"name": "Positive CONDITIONING", "type": "CONDITIONING", "links": [101], "shape": 3, "slot_index": 0}, {"name": "Negative CONDITIONING", "type": "CONDITIONING", "links": [99], "shape": 3, "slot_index": 1}, {"name": "CLIP", "type": "CLIP", "links": null, "shape": 3}, {"name": "Positive text", "type": "STRING", "links": null, "shape": 3}, {"name": "Negative text", "type": "STRING", "links": null, "shape": 3}], "title": "Prompt(Top+)(Bot-)", "properties": {"Node name for S&R": "Prompts"}, "widgets_values": [" {\n        \"0\": \"Juicy Red Lipstick, Dark Eye Shadow, Hazel Eyes, torn up nylon hosiery worn on legs, ripped blue mini skirt, frayed black crop top, loosely fitted open red leather jacket, black fingerless gloves, Scarlet Red High Heels,   sunset in background <lora:Girl Running In Rain:0.5> hands clenched in the shape of fists, female focus, elaborate features, extremely detailed pretty face, bright pupils, vibrant makeup, wide hips, white hair, the image is of a well endowed & busty cartoon girl running away from something, 1girl, fingerless gloves, gloves, solo, skirt, yellow eyes, navel, midriff, white hair, jacket, lipstick, open mouth, black gloves, makeup, explosion, throwing rock, being chased \u300akinetic force, desperate escape\u300b \u300aclose to face\u300b \u300abust up angle\u300breflective eyes and teeth gleaming in the dark (masterpiece, best quality), (((cleavage, solo))), ,((best quality, 1girl,)) ray tracing, ultra detailed,\n        \"75\": \"Juicy Red Lipstick, Dark Eye Shadow, Hazel Eyes, torn up nylon hosiery worn on legs, ripped blue mini skirt, frayed black crop top, loosely fitted open red leather jacket, black fingerless gloves, Scarlet Red High Heels,  female focus, big bouncy butt, elaborate features, extremely detailed pretty face, bright pupils, vibrant makeup, wide hips, white hair, the image is of a well endowed & busty cartoon girl running away from something, 1girl, fingerless gloves, gloves, solo, skirt, yellow eyes, navel, midriff, white hair, jacket, lipstick, open mouth, black gloves, makeup, breasts, large breasts, huge breasts, gigantic breasts, 1girl, short hair, risqu\u00e9 clothes, white hair, explosion, frown, throwing rock, being chased \u300akinetic force, desperate escape\u300b \u300aclose to face\u300b \u300abust up angle\u300breflective eyes and teeth gleaming in the dark, gigabreast, sagging breast, 1girl, (masterpiece, best quality), newest, intricate details, ai-generated, (((huge breasts, cleavage, solo))), ,((best quality, 1girl,)) ray tracing, ultra detailed, high resolution, 8k, UHD, wallpaper,\n        \"150\": \"Juicy Red Lipstick, Dark Eye Shadow, Hazel Eyes, torn up nylon hosiery worn on legs, ripped blue mini skirt, frayed black crop top, loosely fitted open red leather jacket, black fingerless gloves, Scarlet Red High Heels,  harvest moon in the night sky, elaborate features, extremely detailed pretty face, bright pupils, vibrant makeup, wide hips, white hair, the image is of a well endowed & busty cartoon girl running away from something, 1girl, fingerless gloves, gloves, solo, skirt, yellow eyes, navel, midriff, white hair, jacket, lipstick,  open mouth, black gloves, makeup, breasts, large breasts, huge breasts, gigantic breasts, 1girl, short hair, risqu\u00e9 clothes \u300akinetic force, desperate escape\u300b,falling debris from the sky, \u300aclose to face\u300b \u300abust up angle\u300breflective eyes and teeth gleaming in the dark, gigabreast, sagging breast, 1girl, (masterpiece, best quality), newest, intricate details, ai-generated, (((huge breasts, cleavage, solo))), ,((best quality, 1girl,)) ray tracing, ultra detailed, high resolution, 8k, UHD, wallpaper, lacy pink undergarments, cleavage visible,\n        \"250\": \"Juicy Red Lipstick, Dark Eye Shadow, Hazel Eyes, torn up nylon hosiery worn on legs, ripped blue mini skirt, frayed black crop top, loosely fitted open red leather jacket, black fingerless gloves, Scarlet Red High Heels,  female focus, Anime Style, an athletic female, elaborate features, extremely detailed pretty face, bright pupils, vibrant makeup, wide hips, white hair, the image is of a well endowed & busty cartoon girl running away from something, 1girl, fingerless gloves, gloves, solo, skirt, yellow eyes, navel, midriff, white hair, jacket, lipstick, open mouth, black gloves, makeup, breasts, large breasts, huge breasts, gigantic breasts, 1girl, short hair, risqu\u00e9 clothes\u300akinetic force, desperate escape\u300b,falling debris from the sky,\u300aclose to face\u300b \u300abust up angle\u300breflective eyes and teeth gleaming in the dark, gigabreast, sagging breast, 1girl, (masterpiece, best quality), newest, intricate details, ai-generated, (((huge breasts, cleavage, solo))), ,((best quality, 1girl,)) ray tracing, ultra detailed, high resolution, 8k, UHD, wallpaper,\n        \"350\": \"Juicy Red Lipstick, Dark Eye Shadow, Hazel Eyes, torn up nylon hosiery worn on legs, ripped blue mini skirt, frayed black crop top, loosely fitted open red leather jacket, black fingerless gloves, Scarlet Red High Heels,  female focus, Anime Style, elaborate features, extremely detailed pretty face, bright pupils, vibrant makeup, wide hips, white hair, the image is of a cartoon girl running away from something, 1girl, fingerless gloves, gloves, solo, skirt, yellow eyes, navel, midriff, white hair, jacket, lipstick, open mouth, black gloves, makeup, 1girl, short hair, risqu\u00e9 clothes, throwing rock, \u300akinetic force, desperate escape\u300b,falling debris from the sky,\u300aclose to face\u300b \u300abust up angle\u300breflective eyes and teeth gleaming in the dark, 1girl, (masterpiece, best quality), newest, intricate details, ai-generated, (((cleavage, solo))), ,((best quality, 1girl,)) ray tracing, ultra detailed, high resolution, 8k, UHD, wallpaper,\n        \"450\": \"Juicy Red Lipstick, Dark Eye Shadow, Hazel Eyes, torn up nylon hosiery worn on legs, ripped blue mini skirt, frayed black crop top, loosely fitted open red leather jacket, black fingerless gloves, Scarlet Red High Heels,  a sexy female, Busty, exaggerated feminine physique, well endowed, ample breasts, cinematic, epic, elaborate features, extremely detailed pretty face, bright pupils, vibrant makeup, wide hips, white hair, the image is of a well endowed & busty cartoon girl running away from something, 1girl, fingerless gloves, gloves, solo, skirt, yellow eyes, navel, midriff, white hair, jacket, lipstick, open mouth, black gloves, makeup, breasts, large breasts, huge breasts, gigantic breasts, 1girl, short hair, risqu\u00e9 clothes\u300akinetic force, desperate escape\u300b,falling debris from the sky,\u300aclose to face\u300b \u300abust up angle\u300breflective eyes and teeth gleaming in the dark, gigabreast, sagging breast, 1girl, (masterpiece, best quality), newest, intricate details, ai-generated, (((huge breasts, cleavage, solo))), ,((best quality, 1girl,)) ray tracing, ultra detailed, high resolution, 8k, UHD, wallpaper\n    },\n", "lowres, error, cropped, worst quality, low quality, jpeg artifacts, out of frame, watermark, signature, deformed, ugly, mutilated, disfigured, text, extra limbs, face cut, head cut, extra fingers, extra arms, poorly drawn face, mutation, bad proportions, cropped head, malformed limbs, mutated hands, fused fingers, long neck, illustration, painting, drawing, art, sketch, backside, blurry, uncinematic, fake, male, unrealistic, solid background, bland scenery, mushrooms, asian, black woman, black, wild, ugly, deformed, poor quality,"], "color": "#232", "bgcolor": "#353"}, {"id": 93, "type": "CLIPTextEncode", "pos": [622, -690], "size": {"0": 417.5306091308594, "1": 212.57667541503906}, "flags": {}, "order": 22, "mode": 4, "inputs": [{"name": "clip", "type": "CLIP", "link": 97}], "outputs": [{"name": "CONDITIONING", "type": "CONDITIONING", "links": [102], "shape": 3, "slot_index": 0}], "title": "Upscale Detailer (+Prompt)", "properties": {"Node name for S&R": "CLIPTextEncode"}, "widgets_values": ["Juicy Red Lipstick, Dark Eye Shadow, Hazel Eyes, torn up nylon hosiery worn on legs, ripped blue mini skirt, frayed black crop top, loosely fitted open red leather jacket, black fingerless gloves, Scarlet Red High Heels,   sunset in background <lora:Girl Running In Rain:0.5> hands clenched in the shape of fists, female focus, elaborate features, extremely detailed pretty face, bright pupils, vibrant makeup, wide hips, white hair, the image is of a well endowed & busty cartoon girl running away from something, 1girl, fingerless gloves, gloves, solo, skirt, yellow eyes, navel, midriff, white hair, jacket, lipstick, open mouth, black gloves, makeup, explosion, throwing rock, being chased \u300akinetic force, desperate escape\u300b \u300aclose to face\u300b \u300abust up angle\u300breflective eyes and teeth gleaming in the dark (masterpiece, best quality), (((cleavage, solo))), ,((best quality, 1girl,)) ray tracing, ultra detailed,"], "color": "#ffcb50", "bgcolor": "#ffb73c"}, {"id": 98, "type": "CLIPTextEncode", "pos": [621, -435], "size": {"0": 413.6437683105469, "1": 145.36642456054688}, "flags": {}, "order": 23, "mode": 4, "inputs": [{"name": "clip", "type": "CLIP", "link": 104, "slot_index": 0}], "outputs": [{"name": "CONDITIONING", "type": "CONDITIONING", "links": [103], "shape": 3, "slot_index": 0}], "title": "Upscale Detailer (-Prompt)", "properties": {"Node name for S&R": "CLIPTextEncode"}, "widgets_values": ["lowres, error, cropped, worst quality, low quality, jpeg artifacts, out of frame, watermark, signature, deformed, ugly, mutilated, disfigured, text, extra limbs, face cut, head cut, extra fingers, extra arms, poorly drawn face, mutation, bad proportions, cropped head, malformed limbs, mutated hands, fused fingers, long neck, illustration, painting, drawing, art, sketch, backside, blurry, uncinematic, fake, male, unrealistic, solid background, bland scenery, mushrooms, asian, black woman, black, wild, ugly, deformed, poor quality,\n"], "color": "#ffb73c", "bgcolor": "#ffa328"}, {"id": 15, "type": "KSampler", "pos": [623, -254], "size": {"0": 264.4452819824219, "1": 230}, "flags": {"collapsed": false}, "order": 44, "mode": 4, "inputs": [{"name": "model", "type": "MODEL", "link": 16}, {"name": "positive", "type": "CONDITIONING", "link": 102}, {"name": "negative", "type": "CONDITIONING", "link": 103}, {"name": "latent_image", "type": "LATENT", "link": 15}, {"name": "seed", "type": "INT", "link": 83, "widget": {"name": "seed"}}, {"name": "steps", "type": "INT", "link": 85, "widget": {"name": "steps"}}, {"name": "cfg", "type": "FLOAT", "link": null, "widget": {"name": "cfg"}}], "outputs": [{"name": "LATENT", "type": "LATENT", "links": [20], "shape": 3, "slot_index": 0}], "properties": {"Node name for S&R": "KSampler"}, "widgets_values": [351863803273899, "randomize", 30, 7.5, "euler_ancestral", "karras", 0.6], "color": "#ffa328", "bgcolor": "#ff8f14"}, {"id": 66, "type": "mxSlider2D", "pos": [-415, -577], "size": [653.6124563532255, 574.7015573301879], "flags": {}, "order": 12, "mode": 4, "outputs": [{"name": "", "type": "INT", "links": [74], "shape": 3, "slot_index": 0}, {"name": "", "type": "INT", "links": [75], "shape": 3, "slot_index": 1}], "title": "Resolution", "properties": {"valueX": 512, "valueY": 512, "minX": 0, "minY": 0, "maxX": 1024, "maxY": 1024, "stepX": 128, "stepY": 128, "decimalsX": 0, "decimalsY": 0, "snap": true, "dots": true, "frame": true, "frameAlert": 0, "Node name for S&R": "mxSlider2D"}, "widgets_values": [512, 512, 512, 512, 0, 0], "color": "#232", "bgcolor": "#353"}, {"id": 6, "type": "ADE_AnimateDiffLoaderWithContext", "pos": [590, -1020], "size": {"0": 371.4809875488281, "1": 230}, "flags": {}, "order": 31, "mode": 0, "inputs": [{"name": "model", "type": "MODEL", "link": 94}, {"name": "context_options", "type": "CONTEXT_OPTIONS", "link": 5, "slot_index": 1}, {"name": "motion_lora", "type": "MOTION_LORA", "link": 95}, {"name": "motion_model_settings", "type": "MOTION_MODEL_SETTINGS", "link": null}, {"name": "sample_settings", "type": "sample_settings", "link": null}, {"name": "ad_keyframes", "type": "AD_KEYFRAMES", "link": null}], "outputs": [{"name": "MODEL", "type": "MODEL", "links": [11, 16], "shape": 3, "slot_index": 0}], "properties": {"Node name for S&R": "ADE_AnimateDiffLoaderWithContext"}, "widgets_values": ["improved3DMotion_improved3DV1.ckpt", "sqrt_linear (AnimateDiff)", 1, false], "color": "#323", "bgcolor": "#535"}, {"id": 14, "type": "LatentUpscaleBy", "pos": [878, -740], "size": {"0": 254.94110107421875, "1": 88.60637664794922}, "flags": {"collapsed": true}, "order": 40, "mode": 4, "inputs": [{"name": "samples", "type": "LATENT", "link": 25}], "outputs": [{"name": "LATENT", "type": "LATENT", "links": [15], "shape": 3, "slot_index": 0}], "properties": {"Node name for S&R": "LatentUpscaleBy"}, "widgets_values": ["nearest-exact", 2], "color": "#ff8f14", "bgcolor": "#ff7b00"}, {"id": 40, "type": "VHS_VideoCombine", "pos": [1055, -720], "size": [247.86920166015625, 528.3700130923763], "flags": {"collapsed": false}, "order": 46, "mode": 4, "inputs": [{"name": "images", "type": "IMAGE", "link": 60}, {"name": "audio", "type": "VHS_AUDIO", "link": null}, {"name": "meta_batch", "type": "VHS_BatchManager", "link": null}, {"name": "frame_rate", "type": "FLOAT", "link": null, "widget": {"name": "frame_rate"}}], "outputs": [{"name": "Filenames", "type": "VHS_FILENAMES", "links": null, "shape": 3}], "title": "Video Output 2 (Upscale)", "properties": {"Node name for S&R": "VHS_VideoCombine"}, "widgets_values": {"frame_rate": 10, "loop_count": 0, "filename_prefix": "AnimateDiff", "format": "video/h264-mp4", "pix_fmt": "yuv420p", "crf": 20, "save_metadata": true, "pingpong": false, "save_output": true, "videopreview": {"hidden": false, "paused": true, "params": {"filename": "AnimateDiff_00008.mp4", "subfolder": "", "type": "output", "format": "video/h264-mp4"}}}, "color": "#ffa914", "bgcolor": "#ff9500"}, {"id": 41, "type": "VHS_VideoCombine", "pos": [259, -598], "size": [330.7361145019531, 610.7361145019531], "flags": {"collapsed": false}, "order": 43, "mode": 4, "inputs": [{"name": "images", "type": "IMAGE", "link": 61}, {"name": "audio", "type": "VHS_AUDIO", "link": null}, {"name": "meta_batch", "type": "VHS_BatchManager", "link": null}, {"name": "frame_rate", "type": "FLOAT", "link": null, "widget": {"name": "frame_rate"}}], "outputs": [{"name": "Filenames", "type": "VHS_FILENAMES", "links": null, "shape": 3, "slot_index": 0}], "title": "Video Output 1 (Basic)", "properties": {"Node name for S&R": "VHS_VideoCombine"}, "widgets_values": {"frame_rate": 10, "loop_count": 0, "filename_prefix": "AnimateDiff", "format": "video/h264-mp4", "pix_fmt": "yuv420p", "crf": 20, "save_metadata": true, "pingpong": false, "save_output": true, "videopreview": {"hidden": false, "paused": true, "params": {"filename": "AnimateDiff_00007.mp4", "subfolder": "", "type": "output", "format": "video/h264-mp4"}}}, "color": "#232", "bgcolor": "#353"}, {"id": 79, "type": "VHS_VideoCombine", "pos": [-404, 155], "size": [525.536865234375, 286], "flags": {}, "order": 33, "mode": 4, "inputs": [{"name": "images", "type": "IMAGE", "link": 80}, {"name": "audio", "type": "VHS_AUDIO", "link": null}, {"name": "meta_batch", "type": "VHS_BatchManager", "link": null}, {"name": "frame_rate", "type": "FLOAT", "link": null, "widget": {"name": "frame_rate"}}], "outputs": [{"name": "Filenames", "type": "VHS_FILENAMES", "links": null, "shape": 3}], "title": "Video Output 5 (ControlNet)", "properties": {"Node name for S&R": "VHS_VideoCombine"}, "widgets_values": {"frame_rate": 8, "loop_count": 0, "filename_prefix": "AnimateDiff", "format": "video/h264-mp4", "pix_fmt": "yuv420p", "crf": 19, "save_metadata": true, "pingpong": false, "save_output": true, "videopreview": {"hidden": true, "paused": false, "params": {"filename": "AnimateDiff_00009.mp4", "subfolder": "", "type": "output", "format": "video/h264-mp4"}}}, "color": "#223", "bgcolor": "#335"}, {"id": 78, "type": "AIO_Preprocessor", "pos": [-759.9862255842144, 99.65155428173784], "size": {"0": 315, "1": 82}, "flags": {}, "order": 28, "mode": 4, "inputs": [{"name": "image", "type": "IMAGE", "link": 79}, {"name": "resolution", "type": "INT", "link": 89, "widget": {"name": "resolution"}}], "outputs": [{"name": "IMAGE", "type": "IMAGE", "links": [80], "shape": 3, "slot_index": 0}], "properties": {"Node name for S&R": "AIO_Preprocessor"}, "widgets_values": ["DepthAnythingPreprocessor", 512], "color": "#223", "bgcolor": "#335"}, {"id": 60, "type": "VHS_LoadVideo", "pos": [387, 295], "size": [309.9366149902344, 262], "flags": {}, "order": 13, "mode": 4, "inputs": [{"name": "meta_batch", "type": "VHS_BatchManager", "link": null}], "outputs": [{"name": "IMAGE", "type": "IMAGE", "links": [68], "shape": 3, "slot_index": 0}, {"name": "frame_count", "type": "INT", "links": null, "shape": 3}, {"name": "audio", "type": "VHS_AUDIO", "links": [73], "shape": 3, "slot_index": 2}, {"name": "video_info", "type": "VHS_VIDEOINFO", "links": null, "shape": 3}], "title": "Load Video 4 BG Removal!", "properties": {"Node name for S&R": "VHS_LoadVideo"}, "widgets_values": {"video": "AnimateDiff_00008.mp4", "force_rate": 0, "force_size": "Disabled", "custom_width": 512, "custom_height": 512, "frame_load_cap": 0, "skip_first_frames": 0, "select_every_nth": 1, "choose video to upload": "image", "videopreview": {"hidden": true, "paused": false, "params": {"frame_load_cap": 0, "skip_first_frames": 0, "force_rate": 0, "filename": "AnimateDiff_00008.mp4", "type": "input", "format": "video/mp4", "select_every_nth": 1}}}}, {"id": 77, "type": "VHS_LoadVideo", "pos": [-754, 234], "size": [332.8690490722656, 589.3696395507812], "flags": {}, "order": 14, "mode": 4, "inputs": [{"name": "meta_batch", "type": "VHS_BatchManager", "link": null}], "outputs": [{"name": "IMAGE", "type": "IMAGE", "links": [79], "shape": 3, "slot_index": 0}, {"name": "frame_count", "type": "INT", "links": null, "shape": 3}, {"name": "audio", "type": "VHS_AUDIO", "links": [], "shape": 3, "slot_index": 2}, {"name": "video_info", "type": "VHS_VIDEOINFO", "links": null, "shape": 3}], "title": "Load Video 4 ControlNet", "properties": {"Node name for S&R": "VHS_LoadVideo"}, "widgets_values": {"video": "AnimateDiff_00008.mp4", "force_rate": 0, "force_size": "Disabled", "custom_width": 512, "custom_height": 512, "frame_load_cap": 0, "skip_first_frames": 0, "select_every_nth": 1, "choose video to upload": "image", "videopreview": {"hidden": false, "paused": true, "params": {"frame_load_cap": 0, "skip_first_frames": 0, "force_rate": 0, "filename": "AnimateDiff_00008.mp4", "type": "input", "format": "video/mp4", "select_every_nth": 1}}}, "color": "#223", "bgcolor": "#335"}, {"id": 7, "type": "ADE_AnimateDiffUniformContextOptions", "pos": [641, -1070], "size": {"0": 315, "1": 270}, "flags": {"collapsed": true}, "order": 15, "mode": 0, "inputs": [{"name": "prev_context", "type": "CONTEXT_OPTIONS", "link": null}, {"name": "view_opts", "type": "VIEW_OPTS", "link": null}], "outputs": [{"name": "CONTEXT_OPTIONS", "type": "CONTEXT_OPTIONS", "links": [5], "shape": 3, "slot_index": 0}], "properties": {"Node name for S&R": "ADE_AnimateDiffUniformContextOptions"}, "widgets_values": [16, 1, 4, "uniform", true, "flat", false, 0, 1], "color": "#223", "bgcolor": "#335"}, {"id": 88, "type": "Fast Groups Bypasser (rgthree)", "pos": {"0": -1182, "1": 69, "2": 0, "3": 0, "4": 0, "5": 0, "6": 0, "7": 0, "8": 0, "9": 0}, "size": {"0": 400.93621826171875, "1": 298}, "flags": {}, "order": 16, "mode": 0, "inputs": [], "outputs": [{"name": "OPT_CONNECTION", "type": "*", "links": null}], "title": "Fast Groups Bypasser (Master Control Board)", "properties": {"matchColors": "", "matchTitle": "", "showNav": true, "sort": "position", "customSortAlphabet": "", "toggleRestriction": "default"}, "color": "#14c7ff", "bgcolor": "#00b3ff"}, {"id": 50, "type": "VHS_LoadVideo", "pos": [735, 100], "size": [302.8198547363281, 262], "flags": {}, "order": 17, "mode": 0, "inputs": [{"name": "meta_batch", "type": "VHS_BatchManager", "link": null}], "outputs": [{"name": "IMAGE", "type": "IMAGE", "links": [63], "shape": 3, "slot_index": 0}, {"name": "frame_count", "type": "INT", "links": null, "shape": 3}, {"name": "audio", "type": "VHS_AUDIO", "links": null, "shape": 3}, {"name": "video_info", "type": "VHS_VIDEOINFO", "links": null, "shape": 3}], "title": "Load Video (Input)", "properties": {"Node name for S&R": "VHS_LoadVideo"}, "widgets_values": {"video": "AnimateDiff_00008.mp4", "force_rate": 0, "force_size": "Disabled", "custom_width": 512, "custom_height": 512, "frame_load_cap": 0, "skip_first_frames": 0, "select_every_nth": 1, "choose video to upload": "image", "videopreview": {"hidden": true, "paused": false, "params": {"frame_load_cap": 0, "skip_first_frames": 0, "force_rate": 0, "filename": "AnimateDiff_00008.mp4", "type": "input", "format": "video/mp4", "select_every_nth": 1}}}, "color": "#432", "bgcolor": "#653"}, {"id": 52, "type": "ImageUpscaleWithModel", "pos": [1071, 426], "size": {"0": 226.8000030517578, "1": 46}, "flags": {}, "order": 29, "mode": 0, "inputs": [{"name": "upscale_model", "type": "UPSCALE_MODEL", "link": 64}, {"name": "image", "type": "IMAGE", "link": 63}], "outputs": [{"name": "IMAGE", "type": "IMAGE", "links": [65], "shape": 3, "slot_index": 0}], "properties": {"Node name for S&R": "ImageUpscaleWithModel"}, "color": "#432", "bgcolor": "#653"}, {"id": 53, "type": "UpscaleModelLoader", "pos": [1060.9297316199165, 340.35114707199693], "size": {"0": 260.0469665527344, "1": 58}, "flags": {}, "order": 18, "mode": 0, "outputs": [{"name": "UPSCALE_MODEL", "type": "UPSCALE_MODEL", "links": [64], "shape": 3, "slot_index": 0}], "properties": {"Node name for S&R": "UpscaleModelLoader"}, "widgets_values": ["RealESRGAN_x2.pth"], "color": "#432", "bgcolor": "#653"}, {"id": 56, "type": "VHS_VideoCombine", "pos": [1081, 63], "size": [235.1999969482422, 515.1999969482422], "flags": {}, "order": 42, "mode": 0, "inputs": [{"name": "images", "type": "IMAGE", "link": 67}, {"name": "audio", "type": "VHS_AUDIO", "link": null}, {"name": "meta_batch", "type": "VHS_BatchManager", "link": null}, {"name": "frame_rate", "type": "FLOAT", "link": null, "widget": {"name": "frame_rate"}}], "outputs": [{"name": "Filenames", "type": "VHS_FILENAMES", "links": null, "shape": 3}], "title": "Export Video (Output)", "properties": {"Node name for S&R": "VHS_VideoCombine"}, "widgets_values": {"frame_rate": 8, "loop_count": 0, "filename_prefix": "AnimateDiff", "format": "video/h264-mp4", "pix_fmt": "yuv420p", "crf": 19, "save_metadata": true, "pingpong": false, "save_output": true, "videopreview": {"hidden": false, "paused": false, "params": {"filename": "AnimateDiff_00011.mp4", "subfolder": "", "type": "output", "format": "video/h264-mp4"}}}, "color": "#432", "bgcolor": "#653"}, {"id": 49, "type": "RIFE VFI", "pos": [719, 390], "size": {"0": 319.20001220703125, "1": 202.00149536132812}, "flags": {}, "order": 38, "mode": 0, "inputs": [{"name": "frames", "type": "IMAGE", "link": 66}, {"name": "optional_interpolation_states", "type": "INTERPOLATION_STATES", "link": null}], "outputs": [{"name": "IMAGE", "type": "IMAGE", "links": [67], "shape": 3, "slot_index": 0}], "properties": {"Node name for S&R": "RIFE VFI"}, "widgets_values": ["rife49.pth", 5, 2, true, true, 1], "color": "#432", "bgcolor": "#653"}], "links": [[5, 7, 0, 6, 1, "CONTEXT_OPTIONS"], [11, 6, 0, 8, 0, "MODEL"], [12, 8, 0, 12, 0, "LATENT"], [13, 11, 0, 12, 1, "VAE"], [15, 14, 0, 15, 3, "LATENT"], [16, 6, 0, 15, 0, "MODEL"], [20, 15, 0, 16, 0, "LATENT"], [21, 11, 0, 16, 1, "VAE"], [25, 8, 0, 14, 0, "LATENT"], [60, 16, 0, 40, 0, "IMAGE"], [61, 12, 0, 41, 0, "IMAGE"], [63, 50, 0, 52, 1, "IMAGE"], [64, 53, 0, 52, 0, "UPSCALE_MODEL"], [65, 52, 0, 54, 0, "IMAGE"], [66, 54, 0, 49, 0, "IMAGE"], [67, 49, 0, 56, 0, "IMAGE"], [68, 60, 0, 61, 0, "IMAGE"], [69, 61, 0, 62, 1, "IMAGE"], [70, 63, 0, 62, 0, "RMBGMODEL"], [71, 62, 0, 64, 0, "IMAGE"], [72, 64, 0, 65, 0, "IMAGE"], [73, 60, 2, 65, 1, "VHS_AUDIO"], [74, 66, 0, 75, 0, "INT"], [75, 66, 1, 75, 1, "INT"], [76, 67, 0, 75, 2, "INT"], [77, 75, 0, 8, 3, "LATENT"], [79, 77, 0, 78, 0, "IMAGE"], [80, 78, 0, 79, 0, "IMAGE"], [83, 13, 0, 15, 4, "INT"], [84, 13, 0, 8, 4, "INT"], [85, 80, 0, 15, 5, "INT"], [86, 80, 0, 8, 5, "INT"], [89, 82, 0, 78, 1, "INT"], [90, 76, 0, 85, 0, "MOTION_LORA"], [94, 5, 0, 6, 0, "MODEL"], [95, 85, 0, 6, 2, "MOTION_LORA"], [96, 5, 1, 91, 0, "CLIP"], [97, 5, 1, 93, 0, "CLIP"], [99, 91, 1, 8, 2, "CONDITIONING"], [101, 91, 0, 8, 1, "CONDITIONING"], [102, 93, 0, 15, 1, "CONDITIONING"], [103, 98, 0, 15, 2, "CONDITIONING"], [104, 5, 1, 98, 0, "CLIP"], [106, 5, 0, 103, 0, "MODEL"], [107, 5, 1, 103, 1, "CLIP"], [108, 103, 0, 102, 0, "MODEL"], [109, 103, 1, 105, 0, "CLIP"], [110, 105, 0, 102, 1, "CLIP"], [111, 11, 0, 102, 2, "VAE"], [114, 115, 0, 116, 0, "FLOAT"], [118, 119, 0, 120, 0, "FLOAT"]], "groups": [{"title": "Start", "bounding": [-1410, -768, 2017, 787], "color": "#00ff4c", "font_size": 24, "locked": false}, {"title": "Level_1_Upscale", "bounding": [614, -768, 710, 788], "color": "#ff7b00", "font_size": 24, "locked": false}, {"title": "ControlNet", "bounding": [-763, 29, 903, 565], "color": "#88A", "font_size": 24, "locked": false}, {"title": "BG Removal", "bounding": [154, 29, 562, 565], "color": "#f5f5f5", "font_size": 24, "locked": false}, {"title": "Add Frames!", "bounding": [725, 32, 600, 567], "color": "#b58b2a", "font_size": 24, "locked": false}, {"title": "Lora's", "bounding": [-1040, -1026, 1627, 236], "color": "#a1309b", "font_size": 24, "locked": false}, {"title": "Extra's", "bounding": [964, -1096, 352, 319], "color": "#3f789e", "font_size": 24, "locked": false}], "config": {}, "extra": {"ds": {"scale": 1.0610764609500007, "offset": [354.68326576225894, 94.18674377395625]}}, "version": 0.4}